setup.py
aws4o/__init__.py
aws4o/aws4o.py
aws4o/aws4o_py27console.py
aws4o/aws4o_py36console.py
aws4o/version.py
aws4o.egg-info/PKG-INFO
aws4o.egg-info/SOURCES.txt
aws4o.egg-info/dependency_links.txt
aws4o.egg-info/not-zip-safe
aws4o.egg-info/requires.txt
aws4o.egg-info/top_level.txt
bin/aws4o