Metadata-Version: 1.0
Name: aws4o
Version: 0.3.1
Summary: AWS Console Access via Stanford Single-Sign On
Home-page: https://code.stanford.edu/gsb-circle-research/aws4o
Author: W. Ross Morrow, Luba Gloukhova
Author-email: gsb_circle_research@stanford.edu
License: MIT
Platform: UNKNOWN
